ddgui/__init__.py
ddgui-0.3.dist-info/METADATA
ddgui-0.3.dist-info/WHEEL
ddgui-0.3.dist-info/license.txt
ddgui-0.3.dist-info/top_level.txt
ddgui-0.3.dist-info/RECORD
