Metadata-Version: 2.1
Name: ddgui
Version: 0.3
Summary: This is DD Graphic User Interface
Home-page: UNKNOWN
Author: Limadijaya
Author-email: limasuhendra@Gmail.com
License: UNKNOWN
Platform: UNKNOWN
Classifier: Programming Language :: Python :: 3
Classifier: License :: OSI Approved :: MIT License
Classifier: Operating System :: OS Independent
